prompt_llm/__init__.py
prompt_llm/cli.py
prompt_llm/constants.py
prompt_llm/langchain_util.py
prompt_llm/models.py
prompt_llm/utils.py
prompt_llm-0.1.4.dist-info/METADATA
prompt_llm-0.1.4.dist-info/WHEEL
prompt_llm-0.1.4.dist-info/entry_points.txt
prompt_llm-0.1.4.dist-info/licenses/LICENCE
prompt_llm-0.1.4.dist-info/RECORD
