Metadata-Version: 2.4
Name: prompt_llm
Version: 0.1.4
Summary: A CLI tool to prompt LLMs by reego.software
Project-URL: Homepage, https://github.com/reego-software/prompt_llm
Project-URL: Issues, https://github.com/reego-software/prompt_llm/issues
Author-email: Reego Software <reego.software@gmail.com>
License-File: LICENCE
Classifier: License :: OSI Approved :: MIT License
Classifier: Operating System :: OS Independent
Classifier: Programming Language :: Python :: 3
Requires-Python: >=3.8
Requires-Dist: langchain-cohere
Requires-Dist: langchain-core
Requires-Dist: langchain-fireworks
Requires-Dist: langchain-google-vertexai
Requires-Dist: langchain-groq
Requires-Dist: langchain-mistralai
Requires-Dist: langchain-nvidia-ai-endpoints
Requires-Dist: langchain-openai
Requires-Dist: typer
